aliyunsdkretailcloud/__init__.py
aliyunsdkretailcloud/endpoint.py
aliyunsdkretailcloud/request/__init__.py
aliyunsdkretailcloud/request/v20180313/AddClusterNodeRequest.py
aliyunsdkretailcloud/request/v20180313/AllocatePodConfigRequest.py
aliyunsdkretailcloud/request/v20180313/BatchAddServersRequest.py
aliyunsdkretailcloud/request/v20180313/BindGroupRequest.py
aliyunsdkretailcloud/request/v20180313/BindNodeLabelRequest.py
aliyunsdkretailcloud/request/v20180313/CloseDeployOrderRequest.py
aliyunsdkretailcloud/request/v20180313/CreateAccountRequest.py
aliyunsdkretailcloud/request/v20180313/CreateAppGroupRequest.py
aliyunsdkretailcloud/request/v20180313/CreateAppMonitorsRequest.py
aliyunsdkretailcloud/request/v20180313/CreateAppRequest.py
aliyunsdkretailcloud/request/v20180313/CreateAppResourceAllocRequest.py
aliyunsdkretailcloud/request/v20180313/CreateClusterRequest.py
aliyunsdkretailcloud/request/v20180313/CreateDbRequest.py
aliyunsdkretailcloud/request/v20180313/CreateDeployConfigRequest.py
aliyunsdkretailcloud/request/v20180313/CreateEciConfigRequest.py
aliyunsdkretailcloud/request/v20180313/CreateEnvironmentRequest.py
aliyunsdkretailcloud/request/v20180313/CreateNodeLabelRequest.py
aliyunsdkretailcloud/request/v20180313/CreatePersistentVolumeClaimRequest.py
aliyunsdkretailcloud/request/v20180313/CreatePersistentVolumeRequest.py
aliyunsdkretailcloud/request/v20180313/CreateServiceRequest.py
aliyunsdkretailcloud/request/v20180313/CreateSlbAPRequest.py
aliyunsdkretailcloud/request/v20180313/DeleteAppDetailRequest.py
aliyunsdkretailcloud/request/v20180313/DeleteAppEnvironmentRequest.py
aliyunsdkretailcloud/request/v20180313/DeleteAppGroupRequest.py
aliyunsdkretailcloud/request/v20180313/DeleteAppResourceAllocRequest.py
aliyunsdkretailcloud/request/v20180313/DeleteClusterRequest.py
aliyunsdkretailcloud/request/v20180313/DeleteDatabaseRequest.py
aliyunsdkretailcloud/request/v20180313/DeleteDeployConfigRequest.py
aliyun_python_sdk_retailcloud-2.0.20.dist-info/LICENSE
aliyun_python_sdk_retailcloud-2.0.20.dist-info/METADATA
aliyun_python_sdk_retailcloud-2.0.20.dist-info/WHEEL
aliyun_python_sdk_retailcloud-2.0.20.dist-info/top_level.txt
aliyun_python_sdk_retailcloud-2.0.20.dist-info/RECORD
